<?xml version="1.0"?>
<?mso-application progid="Excel.Sheet"?>
<Workbook xmlns="urn:schemas-microsoft-com:office:spreadsheet"
xmlns:o="urn:schemas-microsoft-com:office:office"
xmlns:x="urn:schemas-microsoft-com:office:excel"
xmlns:ss="urn:schemas-microsoft-com:office:spreadsheet"
xmlns:html="http://www.w3.org/TR/REC-html40">
<ExcelWorkbook xmlns="urn:schemas-microsoft-com:office:excel">
<WindowHeight>17060</WindowHeight>
<WindowWidth>28040</WindowWidth>
<WindowTopX>380</WindowTopX>
<WindowTopY>440</WindowTopY>
<ProtectStructure>False</ProtectStructure>
<ProtectWindows>False</ProtectWindows>
</ExcelWorkbook>
<Styles>
<Style ss:ID="Default" ss:Name="Normal">
<Alignment ss:Vertical="Bottom"/>
<Borders/>
<Font ss:FontName="Calibri" x:Family="Swiss" ss:Size="12" ss:Color="#000000"/>
<Interior/>
<NumberFormat/>
<Protection/>
</Style>
<Style ss:ID="s62">
<Font ss:FontName="Calibri" x:Family="Swiss" ss:Size="12" ss:Color="#000000"
ss:Bold="1"/>
</Style>
<Style ss:ID="s63">
<Font ss:FontName="Calibri" x:Family="Swiss" ss:Size="12" ss:Color="#000000"
ss:Bold="1"/>
<Interior ss:Color="#C0C0C0" ss:Pattern="Solid"/>
</Style>
<Style ss:ID="s64">
<NumberFormat ss:Format="Short Date"/>
</Style>
<Style ss:ID="s65">
<Interior ss:Color="#FFFF00" ss:Pattern="Solid"/>
</Style>
<Style ss:ID="s66">
<Interior ss:Color="#7CFC00" ss:Pattern="Solid"/>
</Style>
</Styles>
<Worksheet ss:Name="Main">
<Table>
<Column ss:AutoFitWidth="1"/>
<Column ss:AutoFitWidth="1"/>
<Column ss:AutoFitWidth="1"/>
<Column ss:AutoFitWidth="1"/>
<Column ss:AutoFitWidth="1"/>
<Column ss:AutoFitWidth="1"/>
<Column ss:AutoFitWidth="1"/>
<Column ss:AutoFitWidth="1"/>
<Column ss:AutoFitWidth="1"/>
<Column ss:AutoFitWidth="1"/>
<Column ss:AutoFitWidth="1"/>
<Column ss:AutoFitWidth="1"/>
<Column ss:AutoFitWidth="1"/>
<Column ss:AutoFitWidth="1"/>
<Column ss:AutoFitWidth="1"/>
<Column ss:AutoFitWidth="1"/>
<Column ss:AutoFitWidth="1"/>
<Column ss:AutoFitWidth="1"/>
<Column ss:AutoFitWidth="1"/>
<Column ss:AutoFitWidth="1"/>
<Column ss:AutoFitWidth="1"/>
<Column ss:AutoFitWidth="1"/>
<Column ss:AutoFitWidth="1"/>
<Column ss:AutoFitWidth="1"/>
<Column ss:AutoFitWidth="1"/>
<Column ss:AutoFitWidth="1"/>
<Column ss:AutoFitWidth="1"/>
<Column ss:AutoFitWidth="1"/>
<Column ss:AutoFitWidth="1"/>
<Column ss:AutoFitWidth="1"/>
<Column ss:AutoFitWidth="1"/>
<Column ss:AutoFitWidth="1"/>
<Column ss:AutoFitWidth="1"/>
<Column ss:AutoFitWidth="1"/>
<Column ss:AutoFitWidth="1"/>
<Column ss:AutoFitWidth="1"/>
<Column ss:AutoFitWidth="1"/>
<Column ss:AutoFitWidth="1"/>
<Column ss:AutoFitWidth="1"/>
<Column ss:AutoFitWidth="1"/>
<Column ss:AutoFitWidth="1"/>
<Column ss:AutoFitWidth="1"/>
<Column ss:AutoFitWidth="1"/>
<Column ss:AutoFitWidth="1"/>
<Column ss:AutoFitWidth="1"/>
<Column ss:AutoFitWidth="1"/>
<Column ss:AutoFitWidth="1"/>
<Row>
<Cell><Data ss:Type="String">ID</Data></Cell>
<Cell><Data ss:Type="String">otisAudiotype</Data></Cell>
<Cell><Data ss:Type="String">ingestAudiotype</Data></Cell>
<Cell><Data ss:Type="String">otisCaptiontype</Data></Cell>
<Cell><Data ss:Type="String">ingestCaptiontype</Data></Cell>
<Cell><Data ss:Type="String">otisAiringtype</Data></Cell>
<Cell><Data ss:Type="String">ingestAiringtype</Data></Cell>
<Cell><Data ss:Type="String">otisEndtime</Data></Cell>
<Cell><Data ss:Type="String">ingestEndtime</Data></Cell>
<Cell><Data ss:Type="String">otisHdlevel</Data></Cell>
<Cell><Data ss:Type="String">ingestHdlevel</Data></Cell>
<Cell><Data ss:Type="String">otisThreed</Data></Cell>
<Cell><Data ss:Type="String">ingestThreed</Data></Cell>
<Cell><Data ss:Type="String">otisPpv</Data></Cell>
<Cell><Data ss:Type="String">ingestPpv</Data></Cell>
<Cell><Data ss:Type="String">otisSeriesid</Data></Cell>
<Cell><Data ss:Type="String">ingestSeriesid</Data></Cell>
<Cell><Data ss:Type="String">otisProgramid</Data></Cell>
<Cell><Data ss:Type="String">ingestProgramid</Data></Cell>
<Cell><Data ss:Type="String">otisShowingtype</Data></Cell>
<Cell><Data ss:Type="String">ingestShowingtype</Data></Cell>
<Cell><Data ss:Type="String">otisStationid</Data></Cell>
<Cell><Data ss:Type="String">ingestStationid</Data></Cell>
<Cell><Data ss:Type="String">otisSap</Data></Cell>
<Cell><Data ss:Type="String">ingestSap</Data></Cell>
<Cell><Data ss:Type="String">otisSubjecttoblackout</Data></Cell>
<Cell><Data ss:Type="String">ingestSubjecttoblackout</Data></Cell>
<Cell><Data ss:Type="String">otisSubtitled</Data></Cell>
<Cell><Data ss:Type="String">ingestSubtitled</Data></Cell>
<Cell><Data ss:Type="String">otisStartTime</Data></Cell>
<Cell><Data ss:Type="String">ingestStartTime</Data></Cell>
<Cell><Data ss:Type="String">otisDvrProgramId</Data></Cell>
<Cell><Data ss:Type="String">ingeDvrProgramId</Data></Cell>
<Cell><Data ss:Type="String">otisDvrseriesid</Data></Cell>
<Cell><Data ss:Type="String">ingestDvrseriesid</Data></Cell>
<Cell><Data ss:Type="String">otisDescriptivevideoservice</Data></Cell>
<Cell><Data ss:Type="String">ingestDescriptivevideoservice</Data></Cell>
<Cell><Data ss:Type="String">otisQuality</Data></Cell>
<Cell><Data ss:Type="String">ingestQuality</Data></Cell>
<Cell><Data ss:Type="String">otisRatingbody</Data></Cell>
<Cell><Data ss:Type="String">ingestRatingbody</Data></Cell>
<Cell><Data ss:Type="String">otisRating</Data></Cell>
<Cell><Data ss:Type="String">ingestRating</Data></Cell>
<Cell><Data ss:Type="String">otisSubrating</Data></Cell>
<Cell><Data ss:Type="String">ingestSubrating</Data></Cell>
<Cell><Data ss:Type="String">OtisUpdateId</Data></Cell>
<Cell><Data ss:Type="String">IngUpdated</Data></Cell>
</Row>

<Row>
<Cell><Data ss:Type="String">2019-05-17~19:50~98066</Data></Cell>
<Cell><Data ss:Type="String">null</Data></Cell>
<Cell><Data ss:Type="String">null</Data></Cell>
<Cell><Data ss:Type="String">null</Data></Cell>
<Cell><Data ss:Type="String">null</Data></Cell>
<Cell><Data ss:Type="String">Live</Data></Cell>
<Cell><Data ss:Type="String">Live</Data></Cell>
<Cell><Data ss:Type="String">2019-05-17 21:30:00</Data></Cell>
<Cell><Data ss:Type="String">2019-05-17 21:30:00</Data></Cell>
<Cell><Data ss:Type="String">1080i</Data></Cell>
<Cell><Data ss:Type="String">1080i</Data></Cell>
<Cell><Data ss:Type="String">false</Data></Cell>
<Cell><Data ss:Type="String">false</Data></Cell>
<Cell><Data ss:Type="String">false</Data></Cell>
<Cell><Data ss:Type="String">false</Data></Cell>
<Cell ss:StyleID="s65"><Data ss:Type="String">319508400002315</Data></Cell>
<Cell ss:StyleID="s65"><Data ss:Type="String">null</Data></Cell>
<Cell><Data ss:Type="String">319508400002315</Data></Cell>
<Cell><Data ss:Type="String">319508400002315</Data></Cell>
<Cell><Data ss:Type="String">null</Data></Cell>
<Cell><Data ss:Type="String">null</Data></Cell>
<Cell><Data ss:Type="String">98066315</Data></Cell>
<Cell><Data ss:Type="String">98066315</Data></Cell>
<Cell><Data ss:Type="String">false</Data></Cell>
<Cell><Data ss:Type="String">false</Data></Cell>
<Cell><Data ss:Type="String">false</Data></Cell>
<Cell><Data ss:Type="String">false</Data></Cell>
<Cell><Data ss:Type="String">false</Data></Cell>
<Cell><Data ss:Type="String">false</Data></Cell>
<Cell><Data ss:Type="String">2019-05-17 19:50:00</Data></Cell>
<Cell><Data ss:Type="String">2019-05-17 19:50:00</Data></Cell>
<Cell><Data ss:Type="String">1222588</Data></Cell>
<Cell><Data ss:Type="String">1222588</Data></Cell>
<Cell ss:StyleID="s65"><Data ss:Type="String">1222588</Data></Cell>
<Cell ss:StyleID="s65"><Data ss:Type="String">null</Data></Cell>
<Cell><Data ss:Type="String">false</Data></Cell>
<Cell><Data ss:Type="String">false</Data></Cell>
<Cell><Data ss:Type="String">HD</Data></Cell>
<Cell><Data ss:Type="String">HD</Data></Cell>
<Cell><Data ss:Type="String">null</Data></Cell>
<Cell><Data ss:Type="String">null</Data></Cell>
<Cell><Data ss:Type="String">null</Data></Cell>
<Cell><Data ss:Type="String">null</Data></Cell>
<Cell><Data ss:Type="String">null</Data></Cell>
<Cell><Data ss:Type="String">null</Data></Cell>
<Cell><Data ss:Type="String">2019-05-16 21:19:37.915948</Data></Cell>
<Cell><Data ss:Type="String">2019-05-16 22:08:55.0</Data></Cell>
</Row>

<Row>
<Cell><Data ss:Type="String">2019-06-01~23:30~52697</Data></Cell>
<Cell><Data ss:Type="String">null</Data></Cell>
<Cell><Data ss:Type="String">null</Data></Cell>
<Cell><Data ss:Type="String">null</Data></Cell>
<Cell><Data ss:Type="String">null</Data></Cell>
<Cell><Data ss:Type="String">null</Data></Cell>
<Cell><Data ss:Type="String">null</Data></Cell>
<Cell ss:StyleID="s65"><Data ss:Type="String">2019-06-02 02:30:00</Data></Cell>
<Cell ss:StyleID="s65"><Data ss:Type="String">2019-06-02 01:30:00</Data></Cell>
<Cell><Data ss:Type="String">1080i</Data></Cell>
<Cell><Data ss:Type="String">1080i</Data></Cell>
<Cell><Data ss:Type="String">false</Data></Cell>
<Cell><Data ss:Type="String">false</Data></Cell>
<Cell><Data ss:Type="String">false</Data></Cell>
<Cell><Data ss:Type="String">false</Data></Cell>
<Cell ss:StyleID="s65"><Data ss:Type="String">133069100002315</Data></Cell>
<Cell ss:StyleID="s65"><Data ss:Type="String">258677400002315</Data></Cell>
<Cell ss:StyleID="s65"><Data ss:Type="String">133069100533315</Data></Cell>
<Cell ss:StyleID="s65"><Data ss:Type="String">258677400002315</Data></Cell>
<Cell><Data ss:Type="String">null</Data></Cell>
<Cell><Data ss:Type="String">null</Data></Cell>
<Cell><Data ss:Type="String">52697315</Data></Cell>
<Cell><Data ss:Type="String">52697315</Data></Cell>
<Cell><Data ss:Type="String">false</Data></Cell>
<Cell><Data ss:Type="String">false</Data></Cell>
<Cell><Data ss:Type="String">false</Data></Cell>
<Cell><Data ss:Type="String">false</Data></Cell>
<Cell><Data ss:Type="String">false</Data></Cell>
<Cell><Data ss:Type="String">false</Data></Cell>
<Cell><Data ss:Type="String">2019-06-01 23:30:00</Data></Cell>
<Cell><Data ss:Type="String">2019-06-01 23:30:00</Data></Cell>
<Cell ss:StyleID="s65"><Data ss:Type="String">null</Data></Cell>
<Cell ss:StyleID="s65"><Data ss:Type="String">199282</Data></Cell>
<Cell ss:StyleID="s65"><Data ss:Type="String">150289</Data></Cell>
<Cell ss:StyleID="s65"><Data ss:Type="String">199282</Data></Cell>
<Cell><Data ss:Type="String">false</Data></Cell>
<Cell><Data ss:Type="String">false</Data></Cell>
<Cell><Data ss:Type="String">HD</Data></Cell>
<Cell><Data ss:Type="String">HD</Data></Cell>
<Cell><Data ss:Type="String">urn:v-chip</Data></Cell>
<Cell><Data ss:Type="String">urn:v-chip</Data></Cell>
<Cell><Data ss:Type="String">TVG</Data></Cell>
<Cell><Data ss:Type="String">TVG</Data></Cell>
<Cell><Data ss:Type="String">null</Data></Cell>
<Cell><Data ss:Type="String">null</Data></Cell>
<Cell><Data ss:Type="String">2019-05-17 00:22:57.216084</Data></Cell>
<Cell><Data ss:Type="String">2019-05-16 22:10:09.0</Data></Cell>
</Row>

<Row>
<Cell><Data ss:Type="String">2019-05-18~09:45~15717</Data></Cell>
<Cell><Data ss:Type="String">null</Data></Cell>
<Cell><Data ss:Type="String">null</Data></Cell>
<Cell><Data ss:Type="String">null</Data></Cell>
<Cell><Data ss:Type="String">null</Data></Cell>
<Cell><Data ss:Type="String">null</Data></Cell>
<Cell><Data ss:Type="String">null</Data></Cell>
<Cell><Data ss:Type="String">2019-05-18 10:45:00</Data></Cell>
<Cell><Data ss:Type="String">2019-05-18 10:45:00</Data></Cell>
<Cell><Data ss:Type="String">null</Data></Cell>
<Cell><Data ss:Type="String">null</Data></Cell>
<Cell><Data ss:Type="String">false</Data></Cell>
<Cell><Data ss:Type="String">false</Data></Cell>
<Cell><Data ss:Type="String">false</Data></Cell>
<Cell><Data ss:Type="String">false</Data></Cell>
<Cell><Data ss:Type="String">89112100002315</Data></Cell>
<Cell><Data ss:Type="String">89112100002315</Data></Cell>
<Cell ss:StyleID="s65"><Data ss:Type="String">89112106953315</Data></Cell>
<Cell ss:StyleID="s65"><Data ss:Type="String">89112106433315</Data></Cell>
<Cell><Data ss:Type="String">null</Data></Cell>
<Cell><Data ss:Type="String">null</Data></Cell>
<Cell><Data ss:Type="String">15717315</Data></Cell>
<Cell><Data ss:Type="String">15717315</Data></Cell>
<Cell><Data ss:Type="String">false</Data></Cell>
<Cell><Data ss:Type="String">false</Data></Cell>
<Cell><Data ss:Type="String">false</Data></Cell>
<Cell><Data ss:Type="String">false</Data></Cell>
<Cell><Data ss:Type="String">false</Data></Cell>
<Cell><Data ss:Type="String">false</Data></Cell>
<Cell><Data ss:Type="String">2019-05-18 09:45:00</Data></Cell>
<Cell><Data ss:Type="String">2019-05-18 09:45:00</Data></Cell>
<Cell ss:StyleID="s65"><Data ss:Type="String">null</Data></Cell>
<Cell ss:StyleID="s65"><Data ss:Type="String">1138682</Data></Cell>
<Cell><Data ss:Type="String">36436</Data></Cell>
<Cell><Data ss:Type="String">36436</Data></Cell>
<Cell><Data ss:Type="String">false</Data></Cell>
<Cell><Data ss:Type="String">false</Data></Cell>
<Cell><Data ss:Type="String">SD</Data></Cell>
<Cell><Data ss:Type="String">SD</Data></Cell>
<Cell><Data ss:Type="String">null</Data></Cell>
<Cell><Data ss:Type="String">null</Data></Cell>
<Cell><Data ss:Type="String">null</Data></Cell>
<Cell><Data ss:Type="String">null</Data></Cell>
<Cell><Data ss:Type="String">null</Data></Cell>
<Cell><Data ss:Type="String">null</Data></Cell>
<Cell><Data ss:Type="String">2019-05-16 23:17:05.600168</Data></Cell>
<Cell><Data ss:Type="String">2019-05-07 00:49:54.0</Data></Cell>
</Row>

<Row>
<Cell><Data ss:Type="String">2019-05-17~19:50~54394</Data></Cell>
<Cell><Data ss:Type="String">null</Data></Cell>
<Cell><Data ss:Type="String">null</Data></Cell>
<Cell><Data ss:Type="String">null</Data></Cell>
<Cell><Data ss:Type="String">null</Data></Cell>
<Cell><Data ss:Type="String">Live</Data></Cell>
<Cell><Data ss:Type="String">Live</Data></Cell>
<Cell><Data ss:Type="String">2019-05-17 21:30:00</Data></Cell>
<Cell><Data ss:Type="String">2019-05-17 21:30:00</Data></Cell>
<Cell><Data ss:Type="String">null</Data></Cell>
<Cell><Data ss:Type="String">null</Data></Cell>
<Cell><Data ss:Type="String">false</Data></Cell>
<Cell><Data ss:Type="String">false</Data></Cell>
<Cell><Data ss:Type="String">false</Data></Cell>
<Cell><Data ss:Type="String">false</Data></Cell>
<Cell ss:StyleID="s65"><Data ss:Type="String">319508400002315</Data></Cell>
<Cell ss:StyleID="s65"><Data ss:Type="String">null</Data></Cell>
<Cell><Data ss:Type="String">319508400002315</Data></Cell>
<Cell><Data ss:Type="String">319508400002315</Data></Cell>
<Cell><Data ss:Type="String">null</Data></Cell>
<Cell><Data ss:Type="String">null</Data></Cell>
<Cell><Data ss:Type="String">54394315</Data></Cell>
<Cell><Data ss:Type="String">54394315</Data></Cell>
<Cell><Data ss:Type="String">false</Data></Cell>
<Cell><Data ss:Type="String">false</Data></Cell>
<Cell><Data ss:Type="String">false</Data></Cell>
<Cell><Data ss:Type="String">false</Data></Cell>
<Cell><Data ss:Type="String">false</Data></Cell>
<Cell><Data ss:Type="String">false</Data></Cell>
<Cell><Data ss:Type="String">2019-05-17 19:50:00</Data></Cell>
<Cell><Data ss:Type="String">2019-05-17 19:50:00</Data></Cell>
<Cell><Data ss:Type="String">1222588</Data></Cell>
<Cell><Data ss:Type="String">1222588</Data></Cell>
<Cell ss:StyleID="s65"><Data ss:Type="String">1222588</Data></Cell>
<Cell ss:StyleID="s65"><Data ss:Type="String">null</Data></Cell>
<Cell><Data ss:Type="String">false</Data></Cell>
<Cell><Data ss:Type="String">false</Data></Cell>
<Cell><Data ss:Type="String">SD</Data></Cell>
<Cell><Data ss:Type="String">SD</Data></Cell>
<Cell><Data ss:Type="String">null</Data></Cell>
<Cell><Data ss:Type="String">null</Data></Cell>
<Cell><Data ss:Type="String">null</Data></Cell>
<Cell><Data ss:Type="String">null</Data></Cell>
<Cell><Data ss:Type="String">null</Data></Cell>
<Cell><Data ss:Type="String">null</Data></Cell>
<Cell><Data ss:Type="String">2019-05-16 21:17:24.829922</Data></Cell>
<Cell><Data ss:Type="String">2019-05-16 22:08:55.0</Data></Cell>
</Row>

<Row>
<Cell><Data ss:Type="String">2019-06-01~23:30~88502</Data></Cell>
<Cell><Data ss:Type="String">null</Data></Cell>
<Cell><Data ss:Type="String">null</Data></Cell>
<Cell><Data ss:Type="String">null</Data></Cell>
<Cell><Data ss:Type="String">null</Data></Cell>
<Cell><Data ss:Type="String">null</Data></Cell>
<Cell><Data ss:Type="String">null</Data></Cell>
<Cell ss:StyleID="s65"><Data ss:Type="String">2019-06-02 02:30:00</Data></Cell>
<Cell ss:StyleID="s65"><Data ss:Type="String">2019-06-02 01:30:00</Data></Cell>
<Cell><Data ss:Type="String">null</Data></Cell>
<Cell><Data ss:Type="String">null</Data></Cell>
<Cell><Data ss:Type="String">false</Data></Cell>
<Cell><Data ss:Type="String">false</Data></Cell>
<Cell><Data ss:Type="String">false</Data></Cell>
<Cell><Data ss:Type="String">false</Data></Cell>
<Cell ss:StyleID="s65"><Data ss:Type="String">133069100002315</Data></Cell>
<Cell ss:StyleID="s65"><Data ss:Type="String">258677400002315</Data></Cell>
<Cell ss:StyleID="s65"><Data ss:Type="String">133069100533315</Data></Cell>
<Cell ss:StyleID="s65"><Data ss:Type="String">258677400002315</Data></Cell>
<Cell><Data ss:Type="String">null</Data></Cell>
<Cell><Data ss:Type="String">null</Data></Cell>
<Cell><Data ss:Type="String">88502315</Data></Cell>
<Cell><Data ss:Type="String">88502315</Data></Cell>
<Cell><Data ss:Type="String">false</Data></Cell>
<Cell><Data ss:Type="String">false</Data></Cell>
<Cell><Data ss:Type="String">false</Data></Cell>
<Cell><Data ss:Type="String">false</Data></Cell>
<Cell><Data ss:Type="String">false</Data></Cell>
<Cell><Data ss:Type="String">false</Data></Cell>
<Cell><Data ss:Type="String">2019-06-01 23:30:00</Data></Cell>
<Cell><Data ss:Type="String">2019-06-01 23:30:00</Data></Cell>
<Cell ss:StyleID="s65"><Data ss:Type="String">null</Data></Cell>
<Cell ss:StyleID="s65"><Data ss:Type="String">199282</Data></Cell>
<Cell ss:StyleID="s65"><Data ss:Type="String">150289</Data></Cell>
<Cell ss:StyleID="s65"><Data ss:Type="String">199282</Data></Cell>
<Cell><Data ss:Type="String">false</Data></Cell>
<Cell><Data ss:Type="String">false</Data></Cell>
<Cell><Data ss:Type="String">SD</Data></Cell>
<Cell><Data ss:Type="String">SD</Data></Cell>
<Cell><Data ss:Type="String">urn:v-chip</Data></Cell>
<Cell><Data ss:Type="String">urn:v-chip</Data></Cell>
<Cell><Data ss:Type="String">TVG</Data></Cell>
<Cell><Data ss:Type="String">TVG</Data></Cell>
<Cell><Data ss:Type="String">null</Data></Cell>
<Cell><Data ss:Type="String">null</Data></Cell>
<Cell><Data ss:Type="String">2019-05-17 00:22:12.761921</Data></Cell>
<Cell><Data ss:Type="String">2019-05-09 03:47:24.0</Data></Cell>
</Row>

</Table>
</Worksheet>
</Workbook>

